LICENSE
README.rst
brotli_file.py
setup.cfg
setup.py
brotli_file.egg-info/PKG-INFO
brotli_file.egg-info/SOURCES.txt
brotli_file.egg-info/dependency_links.txt
brotli_file.egg-info/requires.txt
brotli_file.egg-info/top_level.txt